detectk_clickhouse/__init__.py
detectk_clickhouse/collector.py
detectk_clickhouse/storage.py
detectk_collectors_clickhouse-0.1.5.dist-info/METADATA
detectk_collectors_clickhouse-0.1.5.dist-info/WHEEL
detectk_collectors_clickhouse-0.1.5.dist-info/top_level.txt
detectk_collectors_clickhouse-0.1.5.dist-info/RECORD
