Metadata-Version: 2.4
Name: detectk-collectors-clickhouse
Version: 0.1.5
Summary: ClickHouse collector and storage for DetectK
Author-email: Alexei Veselov <alexeiveselov92@gmail.com>
Project-URL: Homepage, https://github.com/alexeiveselov92/detectk
Project-URL: Repository, https://github.com/alexeiveselov92/detectk
Keywords: detectk,clickhouse,monitoring,metrics,collector
Classifier: Development Status :: 3 - Alpha
Classifier: Intended Audience :: Developers
Classifier: Topic :: System :: Monitoring
Classifier: Programming Language :: Python :: 3.10
Classifier: Programming Language :: Python :: 3.11
Classifier: Programming Language :: Python :: 3.12
Requires-Python: >=3.10
Requires-Dist: detectk>=0.1.0
Requires-Dist: clickhouse-driver>=0.2.0
Provides-Extra: dev
Requires-Dist: pytest>=7.0; extra == "dev"
Requires-Dist: pytest-cov>=4.0; extra == "dev"
Requires-Dist: black>=23.0; extra == "dev"
Requires-Dist: ruff>=0.1.0; extra == "dev"
Requires-Dist: mypy>=1.0; extra == "dev"
